channelintensities/GUI.py
channelintensities/__init__.py
channelintensities/analysis.py
channelintensities/core.py
channelintensities/demos.py
channelintensities/plotting.py
channelintensities/run.py
channelintensities/util.py
channelintensities-1.0.0.dist-info/METADATA
channelintensities-1.0.0.dist-info/WHEEL
channelintensities-1.0.0.dist-info/entry_points.txt
channelintensities-1.0.0.dist-info/top_level.txt
channelintensities-1.0.0.dist-info/RECORD
