Metadata-Version: 2.1
Name: channelintensities
Version: 1.0.0
Summary: Package for analyzing microscopy data of channels. Outputs intensities averaged over the width of the channel.
Author-email: Timon Stegmaier <timon@rapid-systems.de>
License: MIT
Project-URL: Source, https://github.com/Teranis/channelintensities
Project-URL: Tracker, https://github.com/Teranis/channelintensities/issues
Project-URL: homepage, https://github.com/Teranis/channelintensities
Keywords: microscopy,intensities,diffusion
Classifier: Programming Language :: Python :: 3
Classifier: License :: OSI Approved :: MIT License
Classifier: Operating System :: OS Independent
Requires-Python: >=3.8
Requires-Dist: colorama<1.0.0,>=0.4.6
Requires-Dist: contourpy<2.0.0,>=1.3.1
Requires-Dist: cycler<1.0.0,>=0.12.1
Requires-Dist: fonttools<5.0.0,>=4.55.2
Requires-Dist: imageio<3.0.0,>=2.36.1
Requires-Dist: kiwisolver<2.0.0,>=1.4.7
Requires-Dist: lazy_loader<1.0.0,>=0.4
Requires-Dist: matplotlib<4.0.0,>=3.9.3
Requires-Dist: networkx<4.0.0,>=3.4.2
Requires-Dist: numpy<3.0.0,>=2.2.0
Requires-Dist: packaging<25.0,>=24.2
Requires-Dist: pandas<3.0.0,>=2.2.3
Requires-Dist: pillow<12.0.0,>=11.0.0
Requires-Dist: pyparsing<4.0.0,>=3.2.0
Requires-Dist: python-dateutil<3.0.0,>=2.9.0.post0
Requires-Dist: pytz<2025.0,>=2024.2
Requires-Dist: scikit-image<1.0.0,>=0.24.0
Requires-Dist: scipy<2.0.0,>=1.14.1
Requires-Dist: shapely<3.0.0,>=2.0.6
Requires-Dist: six<2.0.0,>=1.17.0
Requires-Dist: tifffile<2025.0.0,>=2024.9.20
Requires-Dist: tqdm<5.0.0,>=4.67.1
Requires-Dist: tzdata<2025.0,>=2024.2
